pita_z/.ipynb_checkpoints/__init__-checkpoint.py
pita_z/__init__.py
pita_z/data_modules/.ipynb_checkpoints/data_modules-checkpoint.py
pita_z/data_modules/data_modules.py
pita_z/models/.ipynb_checkpoints/basic_models-checkpoint.py
pita_z/models/.ipynb_checkpoints/fully_supervised_model-checkpoint.py
pita_z/models/.ipynb_checkpoints/pita_model-checkpoint.py
pita_z/models/basic_models.py
pita_z/models/fully_supervised_model.py
pita_z/models/pita_model.py
pita_z/utils/.ipynb_checkpoints/augmentations-checkpoint.py
pita_z/utils/.ipynb_checkpoints/lr_schedulers-checkpoint.py
pita_z/utils/.ipynb_checkpoints/reddening-checkpoint.py
pita_z/utils/augmentations.py
pita_z/utils/lr_schedulers.py
pita_z/utils/reddening.py
pita_z-0.0.1.dist-info/licenses/LICENSE
pita_z-0.0.1.dist-info/WHEEL
pita_z-0.0.1.dist-info/METADATA
pita_z-0.0.1.dist-info/RECORD
