Metadata-Version: 2.4
Name: pita-z
Version: 0.0.1
Summary: This package is the implementation of PITA, which is a semi-supervised image-based photo-z algorithm
Author: Ashod Khederlarian
Author-email: Ashod Khederlarian <ashod.kh12@gmail.com>
License-Expression: MIT
License-File: LICENSE
Classifier: Programming Language :: Python :: 3
Classifier: Operating System :: OS Independent
Requires-Python: >=3.9
Project-URL: Homepage, https://github.com/ashodkh/PITA
